{
  "$schema": "https://schema.management.azure.com/schemas/2019-04-01/deploymentTemplate.json#",
  "contentVersion": "1.0.0.0",
  "parameters": {
    "adminUsername": {
      "type": "string",
      "defaultValue": "azureuser",
      "metadata": {
        "description": "Linux user name for the Virtual Machine. It is user used to SSH to the VM instance."
      }
    },
    "mysqlPassword": {
      "type": "securestring",
      "minLength": 6,
      "maxLength": 32,
      "metadata": {
        "description": "Password for openboxes MySQL user. This user is used by OpenBoxes application"
      }
    },
    "dnsNamePrefix": {
      "type": "string",
      "metadata": {
        "description": "DNS Name for the publicly accessible node. Must be lowercase. It should match with the following regular expression: ^[a-z][a-z0-9-]{1,61}[a-z0-9]$ or it will raise an error."
      }
    },
    "vmSize": {
      "type": "string",
      "defaultValue": "Standard_B2s",
      "allowedValues": [
        "Standard_B2s",
        "Standard_DS1_v2",
        "Standard_D2as_v4",
        "Standard_B2ms",
        "Standard_B1ms"
      ],
      "metadata": {
        "description": "The type of the OB virtual machine used for deployment."
      }
    },
    "ubuntuOSVersion": {
      "type": "string",
      "defaultValue": "18.04-LTS",
      "allowedValues": [
        "18.04-LTS",
        "16.04-LTS"
      ],
      "metadata": {
        "description": "The Ubuntu version for the VM. This will pick a fully patched image of this given Ubuntu version. Allowed values: 18.04-LTS, 16.04-LTS"
      }
    },
    "location": {
      "type": "string",
      "defaultValue": "[resourceGroup().location]",
      "metadata": {
        "description": "Location for all resources."
      }
    },
    "authenticationType": {
      "type": "string",
      "defaultValue": "sshPublicKey",
      "allowedValues": [
        "sshPublicKey",
        "password"
      ],
      "metadata": {
        "description": "Type of authentication to use on the Virtual Machine. SSH key is recommended."
      }
    },
    "adminPasswordOrKey": {
      "type": "securestring",
      "metadata": {
        "description": "SSH Key or password for the Virtual Machine. SSH key is recommended."
      }
    }
  },
  "variables": {
    "vmName": "OB-VM",
    "setupScriptDirectoryUrl": "https://raw.githubusercontent.com/openboxes/openboxes-devops/master/template/",
    "nicName": "[concat(variables('vmName'), '-VmNic')]",
    "addressPrefix": "10.0.0.0/16",
    "subnetName": "[concat(variables('vmName'), '-Subnet')]",
    "subnetPrefix": "10.0.0.0/24",
    "publicIPAddressName": "[concat(variables('vmName'), '-PublicIP')]",
    "publicIPAddressType": "Dynamic",
    "virtualNetworkName": "[concat(variables('vmName'), '-VNET')]",
    "securityGroupName": "[concat(variables('vmName'), '-SecGroup')]",
    "subnetRef": "[resourceId('Microsoft.Network/virtualNetworks/subnets', variables('virtualNetworkName'), variables('subnetName'))]",
    "imagePublisher": "Canonical",
    "imageOffer": "UbuntuServer",
    "vmStorageType": "StandardSSD_LRS",
    "linuxConfiguration": {
      "disablePasswordAuthentication": true,
      "ssh": {
        "publicKeys": [
          {
            "path": "[concat('/home/', parameters('adminUsername'), '/.ssh/authorized_keys')]",
            "keyData": "[parameters('adminPasswordOrKey')]"
          }
        ]
      }
    }
  },
  "resources": [
    {
      "type": "Microsoft.Network/networkSecurityGroups",
      "apiVersion": "2020-11-01",
      "name": "[variables('securityGroupName')]",
      "location": "[parameters('location')]",
      "properties": {
        "securityRules": [
          {
            "name": "default-allow-ssh",
            "properties": {
              "protocol": "Tcp",
              "sourcePortRange": "*",
              "destinationPortRange": "22",
              "sourceAddressPrefix": "*",
              "destinationAddressPrefix": "*",
              "access": "Allow",
              "priority": 1000,
              "direction": "Inbound",
              "sourcePortRanges": [],
              "destinationPortRanges": [],
              "sourceAddressPrefixes": [],
              "destinationAddressPrefixes": []
            }
          },
          {
            "name": "open-port-443",
            "properties": {
              "protocol": "*",
              "sourcePortRange": "*",
              "destinationPortRange": "443",
              "sourceAddressPrefix": "*",
              "destinationAddressPrefix": "*",
              "access": "Allow",
              "priority": 900,
              "direction": "Inbound",
              "sourcePortRanges": [],
              "destinationPortRanges": [],
              "sourceAddressPrefixes": [],
              "destinationAddressPrefixes": []
            }
          },
          {
            "name": "open-port-80",
            "properties": {
              "protocol": "*",
              "sourcePortRange": "*",
              "destinationPortRange": "80",
              "sourceAddressPrefix": "*",
              "destinationAddressPrefix": "*",
              "access": "Allow",
              "priority": 800,
              "direction": "Inbound",
              "sourcePortRanges": [],
              "destinationPortRanges": [],
              "sourceAddressPrefixes": [],
              "destinationAddressPrefixes": []
            }
          }
        ]
      }
    },
    {
      "apiVersion": "2015-06-15",
      "type": "Microsoft.Network/publicIPAddresses",
      "name": "[variables('publicIPAddressName')]",
      "location": "[parameters('location')]",
      "properties": {
        "publicIPAllocationMethod": "[variables('publicIPAddressType')]",
        "dnsSettings": {
          "domainNameLabel": "[parameters('dnsNamePrefix')]"
        }
      }
    },
    {
      "type": "Microsoft.Network/virtualNetworks",
      "apiVersion": "2020-11-01",
      "name": "[variables('virtualNetworkName')]",
      "location": "[parameters('location')]",
      "properties": {
        "addressSpace": {
          "addressPrefixes": [
            "[variables('addressPrefix')]"
          ]
        },
        "subnets": [
          {
            "name": "[variables('subnetName')]",
            "properties": {
              "addressPrefix": "[variables('subnetPrefix')]"
            }
          }
        ]
      }
    },
    {
      "type": "Microsoft.Network/networkInterfaces",
      "apiVersion": "2020-11-01",
      "name": "[variables('nicName')]",
      "location": "[parameters('location')]",
      "dependsOn": [
        "[concat('Microsoft.Network/publicIPAddresses/', variables('publicIPAddressName'))]",
        "[concat('Microsoft.Network/virtualNetworks/', variables('virtualNetworkName'))]",
        "[resourceId('Microsoft.Network/networkSecurityGroups', variables('securityGroupName'))]"
      ],
      "properties": {
        "ipConfigurations": [
          {
            "name": "ipconfig1",
            "properties": {
              "privateIPAllocationMethod": "Dynamic",
              "publicIPAddress": {
                "id": "[resourceId('Microsoft.Network/publicIPAddresses', variables('publicIPAddressName'))]"
              },
              "subnet": {
                "id": "[variables('subnetRef')]"
              },
              "primary": true
              
            }
          }
        ],
        "networkSecurityGroup": {
          "id": "[resourceId('Microsoft.Network/networkSecurityGroups', variables('securityGroupName'))]"
        }
      }
    },
    {
      "type": "Microsoft.Compute/virtualMachines",
      "apiVersion": "2018-06-01",
      "name": "[variables('vmName')]",
      "location": "[parameters('location')]",
      "dependsOn": [
        "[concat('Microsoft.Network/networkInterfaces/', variables('nicName'))]"
      ],
      "properties": {
        "hardwareProfile": {
          "vmSize": "[parameters('vmSize')]"
        },
        "osProfile": {
          "computerName": "[variables('vmName')]",
          "adminUsername": "[parameters('adminUsername')]",
          "adminPassword": "[parameters('adminPasswordOrKey')]",
          "linuxConfiguration": "[if(equals(parameters('authenticationType'), 'password'), json('null'), variables('linuxConfiguration'))]"
        },
        "storageProfile": {
          "imageReference": {
            "publisher": "[variables('imagePublisher')]",
            "offer": "[variables('imageOffer')]",
            "sku": "[parameters('ubuntuOSVersion')]",
            "version": "latest"
          },
          "osDisk": {
            "name": "[concat(variables('vmName'),'_OSDisk')]",
            "caching": "ReadWrite",
            "createOption": "FromImage",
            "managedDisk": {
              "storageAccountType": "[variables('vmStorageType')]"
            }
          }
        },
        "networkProfile": {
          "networkInterfaces": [
            {
              "id": "[resourceId('Microsoft.Network/networkInterfaces',variables('nicName'))]"
            }
          ]
        }
      }
    },
    {
      "type": "Microsoft.Compute/virtualMachines/extensions",
      "name": "[concat(variables('vmName'),'/newuserscript')]",
      "apiVersion": "2015-06-15",
      "location": "[parameters('location')]",
      "dependsOn": [
        "[concat('Microsoft.Compute/virtualMachines/', variables('vmName'))]"
      ],
      "properties": {
        "publisher": "Microsoft.Azure.Extensions",
        "type": "CustomScript",
        "typeHandlerVersion": "2.0",
        "autoUpgradeMinorVersion": true,
        "settings": {
          "fileUris": [
            "[uri(variables('setupScriptDirectoryUrl'),'scripts/ob-vm-setup.sh')]"
          ]
        },
        "protectedSettings": {
          "commandToExecute": "[concat('bash ob-vm-setup.sh ', parameters('mysqlPassword'))]"
        }
      }
    },
    {
      "type": "Microsoft.Network/networkSecurityGroups/securityRules",
      "apiVersion": "2020-11-01",
      "name": "[concat(variables('securityGroupName'), '/default-allow-ssh')]",
      "dependsOn": [
        "[resourceId('Microsoft.Network/networkSecurityGroups', variables('securityGroupName'))]"
      ],
      "properties": {
        "protocol": "Tcp",
        "sourcePortRange": "*",
        "destinationPortRange": "22",
        "sourceAddressPrefix": "*",
        "destinationAddressPrefix": "*",
        "access": "Allow",
        "priority": 1000,
        "direction": "Inbound",
        "sourcePortRanges": [],
        "destinationPortRanges": [],
        "sourceAddressPrefixes": [],
        "destinationAddressPrefixes": []
      }
    },
    {
      "type": "Microsoft.Network/networkSecurityGroups/securityRules",
      "apiVersion": "2020-11-01",
      "name": "[concat(variables('securityGroupName'), '/open-port-80')]",
      "dependsOn": [
        "[resourceId('Microsoft.Network/networkSecurityGroups', variables('securityGroupName'))]"
      ],
      "properties": {
        "protocol": "*",
        "sourcePortRange": "*",
        "destinationPortRange": "80",
        "sourceAddressPrefix": "*",
        "destinationAddressPrefix": "*",
        "access": "Allow",
        "priority": 800,
        "direction": "Inbound",
        "sourcePortRanges": [],
        "destinationPortRanges": [],
        "sourceAddressPrefixes": [],
        "destinationAddressPrefixes": []
      }
    },
    {
      "type": "Microsoft.Network/networkSecurityGroups/securityRules",
      "apiVersion": "2020-11-01",
      "name": "[concat(variables('securityGroupName'), '/open-port-443')]",
      "dependsOn": [
        "[resourceId('Microsoft.Network/networkSecurityGroups', variables('securityGroupName'))]"
      ],
      "properties": {
        "protocol": "*",
        "sourcePortRange": "*",
        "destinationPortRange": "443",
        "sourceAddressPrefix": "*",
        "destinationAddressPrefix": "*",
        "access": "Allow",
        "priority": 900,
        "direction": "Inbound",
        "sourcePortRanges": [],
        "destinationPortRanges": [],
        "sourceAddressPrefixes": [],
        "destinationAddressPrefixes": []
      }
    }
  ],
  "outputs": {}
}